tests/__init__.py
tests/test_example.py
easyxp-1.0.dist-info/METADATA
easyxp-1.0.dist-info/WHEEL
easyxp-1.0.dist-info/top_level.txt
easyxp-1.0.dist-info/RECORD
