Metadata-Version: 2.4
Name: easyxp
Version: 1.0
Summary: Simple add quiver legend toolkit for matplotlib
Home-page: https://github.com/Blissful-Jasper/Easyxp
Author: Xianpu JI
Author-email: xianpuji@hhu.edu.cn
License: MIT
Keywords: quiver legend matplotlib
Classifier: Programming Language :: Python :: 3.10
Classifier: License :: OSI Approved :: MIT License
Classifier: Operating System :: OS Independent
Requires-Python: >=3.6
Requires-Dist: matplotlib
Requires-Dist: numpy
Dynamic: author
Dynamic: author-email
Dynamic: classifier
Dynamic: description
Dynamic: description-content-type
Dynamic: home-page
Dynamic: keywords
Dynamic: license
Dynamic: requires-dist
Dynamic: requires-python
Dynamic: summary
